lab9/lab9.v
module T_flipflop_with_reset (
    input wire clk,    // 时钟信号
    input wire T,      // T输入信号
    input wire reset,  // 复位信号
    output reg Q       // 输出
);

    always @(posedge clk or negedge reset) begin
        if (!reset)
            Q <= 1'b0;   // 复位信号为低电平时，将输出置0
        else if (T)
            Q <= ~Q;     // T为高电平时翻转输出
    end

endmodule

module testbench;

    reg clk;
    reg T;
    reg reset;
    wire Q;

    // 实例化T触发器模块
    T_flipflop_with_reset uut (
        .clk(clk),
        .T(T),
        .reset(reset),
        .Q(Q)
    );

    // 时钟生成
    initial begin
        $dumpfile("wave.vcd");  // 指定输出的波形文件名
        $dumpvars(0, testbench); 
        clk = 0;
        forever #5 clk = ~clk; // 每5个时间单位翻转一次，生成10个时间单位的时钟周期
    end

    // 测试序列
    initial begin
        // 初始化
        reset = 0; T = 0;
        #10 reset = 1;       // 释放复位
        #10 T = 1;           // T = 1，观察Q翻转
        #20 T = 0;           // T = 0，Q保持不变
        #10 T = 1;           // T = 1，Q翻转
        #10 reset = 0;       // 复位信号变低，Q应归0
        #10 reset = 1;       // 复位释放
        #10 T = 1;           // T = 1，Q翻转
        #20 $stop;           // 停止仿真
    end

endmodule

lab9/wave.vcd
$date
	Tue Nov 12 17:40:31 2024
$end
$version
	Icarus Verilog
$end
$timescale
	1s
$end
$scope module testbench $end
$var wire 1 ! Q $end
$var reg 1 " T $end
$var reg 1 # clk $end
$var reg 1 $ reset $end
$scope module uut $end
$var wire 1 " T $end
$var wire 1 # clk $end
$var wire 1 $ reset $end
$var reg 1 ! Q $end
$upscope $end
$upscope $end
$enddefinitions $end
$comment Show the parameter values. $end
$dumpall
$end
#0
$dumpvars
0$
0#
0"
0!
$end
#5
1#
#10
0#
1$
#15
1#
#20
0#
1"
#25
1!
1#
#30
0#
#35
0!
1#
#40
0#
0"
#45
1#
#50
0#
1"
#55
1!
1#
#60
0!
0#
0$
#65
1#
#70
0#
1$
#75
1!
1#
#80
0#
#85
0!
1#
#90
0#
#95
1!
1#
