lab7/lab7.v
module lab7(
    input D0,D1,D2,D3,D4,D5,D6,D7,
    input S2,S1,S0,
    output reg Y
    );
    always @(*) begin
        case({S2,S1,S0})
            3'b000:Y=D0;
            3'b001:Y=D1;
            3'b010:Y=D2;
            3'b011:Y=D3;
            3'b100:Y=D4;
            3'b101:Y=D5;
            3'b110:Y=D6;
            3'b111:Y=D7;
        endcase    
    end    
endmodule
module temp(
    input A,B,C,D,
    output Y
);
lab7 ux(.S2(A),.S1(B),.S0(C),.D0(1'b1),.D1(1'b0),.D2(D),.D3(D),.D4(1'b0),.D5(D),.D6(D),.D7(D),.Y(Y));
endmodule

module test();
reg a_tb,b_tb,c_tb,d_tb;
wire y_tb;
temp ux (.A(a_tb),.B(b_tb),.C(c_tb),.D(d_tb),.Y(y_tb));
initial begin 
    $dumpfile("lab7.vcd");  // 指定输出的波形文件名
    $dumpvars;
    {a_tb,b_tb,c_tb,d_tb}=4'b0000;
       
    #160 $finish;
end
always #10 {a_tb,b_tb,c_tb,d_tb}={a_tb,b_tb,c_tb,d_tb}+1;
endmodule

lab7/lab7.vcd
$date
	Tue Oct 29 21:09:38 2024
$end
$version
	Icarus Verilog
$end
$timescale
	1s
$end
$scope module test $end
$var wire 1 ! y_tb $end
$var reg 1 " a_tb $end
$var reg 1 # b_tb $end
$var reg 1 $ c_tb $end
$var reg 1 % d_tb $end
$scope module ux $end
$var wire 1 " A $end
$var wire 1 # B $end
$var wire 1 $ C $end
$var wire 1 % D $end
$var wire 1 ! Y $end
$scope module ux $end
$var wire 1 & D0 $end
$var wire 1 ' D1 $end
$var wire 1 % D2 $end
$var wire 1 % D3 $end
$var wire 1 ( D4 $end
$var wire 1 % D5 $end
$var wire 1 % D6 $end
$var wire 1 % D7 $end
$var wire 1 $ S0 $end
$var wire 1 # S1 $end
$var wire 1 " S2 $end
$var reg 1 ! Y $end
$upscope $end
$upscope $end
$upscope $end
$enddefinitions $end
$comment Show the parameter values. $end
$dumpall
$end
#0
$dumpvars
0(
0'
1&
0%
0$
0#
0"
1!
$end
#10
1%
#20
0!
1$
0%
#30
1%
#40
1#
0$
0%
#50
1!
1%
#60
0!
1$
0%
#70
1!
1%
#80
0!
1"
0#
0$
0%
#90
1%
#100
1$
0%
#110
1!
1%
#120
0!
1#
0$
0%
#130
1!
1%
#140
0!
1$
0%
#150
1!
1%
#160
0"
0#
0$
0%
